aiojlrpy/__init__.py
aiojlrpy/connection.py
aiojlrpy/const.py
aiojlrpy/exceptions.py
aiojlrpy/stomp.py
aiojlrpy/utils.py
aiojlrpy/vehicle.py
aiojlrpy/websocket.py
aiojlrpy-0.1.5.dist-info/LICENSE
aiojlrpy-0.1.5.dist-info/METADATA
aiojlrpy-0.1.5.dist-info/WHEEL
aiojlrpy-0.1.5.dist-info/top_level.txt
aiojlrpy-0.1.5.dist-info/RECORD
