Metadata-Version: 2.1
Name: aiojlrpy
Version: 0.1.5
Summary: Async Library for JLRIncontrol
Home-page: https://github.com/msp1974/aiojlrpy
Author: msp1974
Author-email: msparker@sky.com
Classifier: Development Status :: 2 - Pre-Alpha
Classifier: Intended Audience :: Developers
Classifier: Programming Language :: Python :: 3.11
Classifier: License :: OSI Approved :: MIT License
Classifier: Operating System :: OS Independent
Requires-Python: >=3.11
License-File: LICENSE
Requires-Dist: aiohttp >=3.9.3
